hapra/Blatt_03/3.1.2/fa.vhdl
library ieee;
use ieee.std_logic_1164.all;

entity fa is
  port (
    a     : in std_logic;
    b     : in std_logic;
    cin   : in std_logic;
    cout  : out std_logic;
    sum   : out std_logic
  );
end fa;

architecture rtl of fa is
  signal o1 : std_logic;
  signal c1 : std_logic;
  signal o2 : std_logic;
  signal c2 : std_logic;
begin
  --ha1
  o1 <= a xor b;
  c1 <= a and b;
  
  --ha2
  o2 <= cin xor o1;
  c2 <= cin and o1;

  cout  <= c1 or c2;
  sum   <= o2; 
end rtl;

hapra/Blatt_03/3.1.2/fa_tb.vhdl
library ieee;
use ieee.std_logic_1164.all;

entity fa_tb is
end fa_tb;

architecture test of fa_tb is
  component fa
    port (
      a     : in std_logic;
      b     : in std_logic;
      cin   : in std_logic;
      cout  : out std_logic;
      sum   : out std_logic
    );
  end component;

signal a, b, cin, cout, sum : std_logic;
begin
  full_adder: fa port map(a => a, b => b, cin => cin, cout => cout, sum => sum);

  process begin
    a   <= '0';
    b   <= '0';
    cin <= '0';
    wait for 10 ns;
    a   <= '0';
    b   <= '0';
    cin <= '1';
    wait for 10 ns;
    a   <= '0';
    b   <= '1';
    cin <= '0';
    wait for 10 ns;
    a   <= '0';
    b   <= '1';
    cin <= '1';
    wait for 10 ns;
    a   <= '1';
    b   <= '0';    
    cin <= '0';
    wait for 10 ns;
    a   <= '1';
    b   <= '0';    
    cin <= '1';
    wait for 10 ns;
    a   <= '1';
    b   <= '1';
    cin <= '0';
    wait for 10 ns;
    a   <= '1';
    b   <= '1';
    cin <= '1';
    wait for 10 ns;
    --TODO add some more test cases
    wait;
  end process;
end test;

Blatt_03/3.1.2/testbench.vcd
$date
  Thu Nov  4 14:45:19 2021
$end
$version
  GHDL v0
$end
$timescale
  1 fs
$end
$scope module standard $end
$upscope $end
$scope module std_logic_1164 $end
$upscope $end
$scope module fa_tb $end
$var reg 1 ! a $end
$var reg 1 " b $end
$var reg 1 # cin $end
$var reg 1 $ cout $end
$var reg 1 % sum $end
$scope module full_adder $end
$var reg 1 & a $end
$var reg 1 ' b $end
$var reg 1 ( cin $end
$var reg 1 ) cout $end
$var reg 1 * sum $end
$var reg 1 + o1 $end
$var reg 1 , c1 $end
$var reg 1 - o2 $end
$var reg 1 . c2 $end
$upscope $end
$upscope $end
$enddefinitions $end
#0
0!
0"
0#
0$
0%
0&
0'
0(
0)
0*
0+
0,
0-
0.
#10000000
1#
1%
1(
1*
1-
#20000000
1"
0#
1%
1'
0(
1*
1+
1-
#30000000
1#
1$
0%
1(
1)
0*
0-
1.
#40000000
1!
0"
0#
0$
1%
1&
0'
0(
0)
1*
1-
0.
#50000000
1#
1$
0%
1(
1)
0*
0-
1.
#60000000
1"
0#
0%
1'
0(
0*
0+
1,
0-
0.
#70000000
1#
1%
1(
1*
1-
