panfiBlatt4/4.2/andgate3.vhdl
library ieee;
use ieee.std_logic_1164.all;

entity andgate3 is
  port (
    input1 : in std_logic;
    input2 : in std_logic;
    input3:  in std_logic;
    and_result : out std_logic
  );
end andgate3;

architecture rtl of andgate3 is
  signal and_gate : std_logic;
begin
  and_gate <= input1 and input2 and input3;
  and_result <= and_gate;
end rtl;

Blatt_04/4.3/notgate.vhdl
library ieee;
use ieee.std_logic_1164.all;

entity notgate is
	port(
		input : in std_logic;
		not_result : out std_logic
	  );
end notgate;

architecture rtl of notgate is
signal not_gate : std_logic;
begin
	not_gate <= NOT input;
	not_result <= not_gate;
end rtl;

panfiBlatt4/4.2/demux14.vhdl
LIBRARY IEEE;
USE IEEE.std_logic_1164.ALL;

ENTITY demux14 IS
    PORT (
        y : IN std_logic_vector(2 DOWNTO 0); 
        sel : IN std_logic_vector(1 DOWNTO 0); 
        y0 : OUT std_logic_vector(2 DOWNTO 0);
        y1 : OUT std_logic_vector(2 DOWNTO 0);
        y2 : OUT std_logic_vector(2 DOWNTO 0);
        y3 : OUT std_logic_vector(2 DOWNTO 0)
        );
END demux14;
  
ARCHITECTURE rtl OF demux14 IS
	COMPONENT andgate3 IS
        PORT (input1 : IN std_logic;
            input2 : IN std_logic;
            input3: IN std_logic;
			and_result: OUT std_logic);
    END COMPONENT;
     COMPONENT notgate IS
		PORT(
			input : in std_logic;
			not_result : out std_logic
		  );
    END COMPONENT;
	signal not_sel : std_logic_vector(1 DOWNTO 0); 
	
BEGIN
	not_output0: notgate port map(input => sel(0), not_result => not_sel(0));
	not_output1: notgate port map(input => sel(1), not_result => not_sel(1));
	and_gate_assignment : for i in 0 to 2 generate
        and_output1: andgate3 port map(input1 => not_sel(1),  input2 => not_sel(0), input3 => y(i), and_result => y0(i));
        and_output2: andgate3 port map(input1 => not_sel(1), input2 => sel(0),  input3 => y(i), and_result => y1(i));
        and_output3: andgate3 port map(input1 => sel(1),  input2 => not_sel(0), input3 => y(i), and_result => y2(i));
        and_output4: andgate3 port map(input1 => sel(1), input2 => sel(0), input3 => y(i), and_result => y3(i));
    end generate and_gate_assignment;

END rtl;

hapra/Blatt_02/2d/1/andgate.vhdl
-- from the ieee libary we use std_logic_1164
-- defines a standard for logic values used in electronic design
-- for more info check the std_logic_1164.vhdl file in ghdl/libraries/ieee
-- ieee libary also defines operators and keywords
library ieee;
use ieee.std_logic_1164.all;
-- define signal (fundamental unit in vhdl) of type std_logic, called and_gate
-- and_gate gets assigned "input1 and input2"
--
--signal and_gate: std_logic;
--and_gate <= input1 and input2;

-- inputs and outputs of a file (andgate.vhdl) are defined in entities (black boxes)
-- entity has port that defines all inputs and outputs of file
-- like a header file (.h)
-- std_logic can have 9 different values, it is part of std_logic_1164 package
-- you can think of it as a single bit
entity andgate is
  port (
    input1 : in std_logic;
    input2 : in std_logic;
    and_result : out std_logic
  );
end andgate;

-- architecture describes functionality of particular entity
-- like .c implementation of a function
-- actually describes the "internal wiring" of block
architecture rtl of andgate is
  -- interconnection signals, constants, or other components
  signal and_gate : std_logic;
begin
  and_gate <= input1 and input2;
  and_result <= transport and_gate after 15 ns;
end rtl;

panfiBlatt4/4.2/demux18.vhdl
LIBRARY IEEE;
USE IEEE.std_logic_1164.ALL;

ENTITY demux18 IS
    PORT (
        y : IN std_logic_vector(2 DOWNTO 0);
        s : IN std_logic_vector(2 DOWNTO 0);
		y0 : OUT std_logic_vector(2 DOWNTO 0);
        y1 : OUT std_logic_vector(2 DOWNTO 0);
        y2 : OUT std_logic_vector(2 DOWNTO 0);
        y3 : OUT std_logic_vector(2 DOWNTO 0);
		y4 : OUT std_logic_vector(2 DOWNTO 0);
        y5 : OUT std_logic_vector(2 DOWNTO 0);
        y6 : OUT std_logic_vector(2 DOWNTO 0);
        y7 : OUT std_logic_vector(2 DOWNTO 0)
    );
END demux18;

ARCHITECTURE rtl OF demux18 IS
	COMPONENT demux14 IS
        PORT (
            y : IN std_logic_vector(2 DOWNTO 0); 
			sel : IN std_logic_vector(1 DOWNTO 0); 
			y0 : OUT std_logic_vector(2 DOWNTO 0);
			y1 : OUT std_logic_vector(2 DOWNTO 0);
			y2 : OUT std_logic_vector(2 DOWNTO 0);
			y3 : OUT std_logic_vector(2 DOWNTO 0)
        );
    END COMPONENT;
	COMPONENT andgate IS
        PORT (input1 : IN std_logic;
            input2 : IN std_logic;
			and_result: OUT std_logic);
    END COMPONENT;
     COMPONENT notgate IS
		PORT(
			input : in std_logic;
			not_result : out std_logic
		  );
    END COMPONENT;
	signal a_out0:  std_logic_vector(2 DOWNTO 0);
	signal a_out1:  std_logic_vector(2 DOWNTO 0);
	signal sel:  std_logic_vector(1 DOWNTO 0);
	signal sel_2_neg: std_logic;
BEGIN
	not_output0: notgate port map(input => s(2), not_result => sel_2_neg);
	and_gate_assignment : for i in 0 to 2 generate
		and_output0: andgate port map(input1 => y(i), input2 => sel_2_neg, and_result => a_out0(i));
		and_output1: andgate port map(input1 => y(i), input2 => s(2), and_result => a_out1(i));
	end generate and_gate_assignment;
	sel(1) <= s(1);
	sel(0) <= s(0);
	demux14_0: demux14 port map(y => a_out0, sel => sel, y0 => y0, y1 => y1, y2 => y2, y3 => y3);
	demux14_1: demux14 port map(y => a_out1, sel => sel, y0 => y4, y1 => y5, y2 => y6, y3 => y7);
	
end rtl;

panfiBlatt4/4.2/demux18_tb.vhdl
library ieee;
use ieee.std_logic_1164.all;

entity demux18_tb is
end demux18_tb;

architecture testbench of demux18_tb is
component demux18
  PORT (
        y : IN std_logic_vector(2 DOWNTO 0);
        s : IN std_logic_vector(2 DOWNTO 0);
		y0 : OUT std_logic_vector(2 DOWNTO 0);
        y1 : OUT std_logic_vector(2 DOWNTO 0);
        y2 : OUT std_logic_vector(2 DOWNTO 0);
        y3 : OUT std_logic_vector(2 DOWNTO 0);
		y4 : OUT std_logic_vector(2 DOWNTO 0);
        y5 : OUT std_logic_vector(2 DOWNTO 0);
        y6 : OUT std_logic_vector(2 DOWNTO 0);
        y7 : OUT std_logic_vector(2 DOWNTO 0)
    );
end component;
	signal y : std_logic_vector(2 DOWNTO 0); 
	signal sel: std_logic_vector(2 DOWNTO 0);
	signal y0 : std_logic_vector(2 DOWNTO 0);
	signal y1: std_logic_vector(2 DOWNTO 0);
	signal y2: std_logic_vector(2 DOWNTO 0);
	signal y3: std_logic_vector(2 DOWNTO 0);
	signal y4: std_logic_vector(2 DOWNTO 0);
	signal y5: std_logic_vector(2 DOWNTO 0);
	signal y6 :std_logic_vector(2 DOWNTO 0); 
	signal y7: std_logic_vector(2 DOWNTO 0);
begin
	y <= "111";
	demux: demux18 port map(y => y, s => sel, y0 => y0, y1 => y1, y2 => y2, y3 => y3, y4 => y4, y5 => y5, y6 => y6, y7 => y7);
    process begin
        sel <= "000";
        wait for 10 ns;
        sel <= "010";
        wait for 10 ns;
        sel <= "001";
        wait for 10 ns;
        sel <= "011";
        wait for 10 ns;
        sel <= "100";
        wait for 10 ns;
        sel <= "110";
        wait for 10 ns;
        sel <= "101";
        wait for 10 ns;
        sel <= "111";
        wait for 10 ns;
        wait;
    end process;
end testbench;

panfiBlatt4/4.2/testbench.vcd
$date
  Fri Dec 11 15:19:35 2020
$end
$version
  GHDL v0
$end
$timescale
  1 fs
$end
$scope module standard $end
$upscope $end
$scope module std_logic_1164 $end
$upscope $end
$scope module demux18_tb $end
$var reg 3 ! y[2:0] $end
$var reg 3 " sel[2:0] $end
$var reg 3 # y0[2:0] $end
$var reg 3 $ y1[2:0] $end
$var reg 3 % y2[2:0] $end
$var reg 3 & y3[2:0] $end
$var reg 3 ' y4[2:0] $end
$var reg 3 ( y5[2:0] $end
$var reg 3 ) y6[2:0] $end
$var reg 3 * y7[2:0] $end
$scope module demux $end
$var reg 3 + y[2:0] $end
$var reg 3 , s[2:0] $end
$var reg 3 - y0[2:0] $end
$var reg 3 . y1[2:0] $end
$var reg 3 / y2[2:0] $end
$var reg 3 0 y3[2:0] $end
$var reg 3 1 y4[2:0] $end
$var reg 3 2 y5[2:0] $end
$var reg 3 3 y6[2:0] $end
$var reg 3 4 y7[2:0] $end
$var reg 3 5 a_out0[2:0] $end
$var reg 3 6 a_out1[2:0] $end
$var reg 2 7 sel[1:0] $end
$var reg 1 8 sel_2_neg $end
$scope module not_output0 $end
$var reg 1 9 input $end
$var reg 1 : not_result $end
$var reg 1 ; not_gate $end
$upscope $end
$scope module and_gate_assignment(0) $end
$scope module and_output0 $end
$var reg 1 < input1 $end
$var reg 1 = input2 $end
$var reg 1 > and_result $end
$var reg 1 ? and_gate $end
$upscope $end
$scope module and_output1 $end
$var reg 1 @ input1 $end
$var reg 1 A input2 $end
$var reg 1 B and_result $end
$var reg 1 C and_gate $end
$upscope $end
$upscope $end
$scope module and_gate_assignment(1) $end
$scope module and_output0 $end
$var reg 1 D input1 $end
$var reg 1 E input2 $end
$var reg 1 F and_result $end
$var reg 1 G and_gate $end
$upscope $end
$scope module and_output1 $end
$var reg 1 H input1 $end
$var reg 1 I input2 $end
$var reg 1 J and_result $end
$var reg 1 K and_gate $end
$upscope $end
$upscope $end
$scope module and_gate_assignment(2) $end
$scope module and_output0 $end
$var reg 1 L input1 $end
$var reg 1 M input2 $end
$var reg 1 N and_result $end
$var reg 1 O and_gate $end
$upscope $end
$scope module and_output1 $end
$var reg 1 P input1 $end
$var reg 1 Q input2 $end
$var reg 1 R and_result $end
$var reg 1 S and_gate $end
$upscope $end
$upscope $end
$scope module demux14_0 $end
$var reg 3 T y[2:0] $end
$var reg 2 U sel[1:0] $end
$var reg 3 V y0[2:0] $end
$var reg 3 W y1[2:0] $end
$var reg 3 X y2[2:0] $end
$var reg 3 Y y3[2:0] $end
$var reg 2 Z not_sel[1:0] $end
$scope module not_output0 $end
$var reg 1 [ input $end
$var reg 1 \ not_result $end
$var reg 1 ] not_gate $end
$upscope $end
$scope module not_output1 $end
$var reg 1 ^ input $end
$var reg 1 _ not_result $end
$var reg 1 ` not_gate $end
$upscope $end
$scope module and_gate_assignment(0) $end
$scope module and_output1 $end
$var reg 1 a input1 $end
$var reg 1 b input2 $end
$var reg 1 c input3 $end
$var reg 1 d and_result $end
$var reg 1 e and_gate $end
$upscope $end
$scope module and_output2 $end
$var reg 1 f input1 $end
$var reg 1 g input2 $end
$var reg 1 h input3 $end
$var reg 1 i and_result $end
$var reg 1 j and_gate $end
$upscope $end
$scope module and_output3 $end
$var reg 1 k input1 $end
$var reg 1 l input2 $end
$var reg 1 m input3 $end
$var reg 1 n and_result $end
$var reg 1 o and_gate $end
$upscope $end
$scope module and_output4 $end
$var reg 1 p input1 $end
$var reg 1 q input2 $end
$var reg 1 r input3 $end
$var reg 1 s and_result $end
$var reg 1 t and_gate $end
$upscope $end
$upscope $end
$scope module and_gate_assignment(1) $end
$scope module and_output1 $end
$var reg 1 u input1 $end
$var reg 1 v input2 $end
$var reg 1 w input3 $end
$var reg 1 x and_result $end
$var reg 1 y and_gate $end
$upscope $end
$scope module and_output2 $end
$var reg 1 z input1 $end
$var reg 1 { input2 $end
$var reg 1 | input3 $end
$var reg 1 } and_result $end
$var reg 1 !" and_gate $end
$upscope $end
$scope module and_output3 $end
$var reg 1 "" input1 $end
$var reg 1 #" input2 $end
$var reg 1 $" input3 $end
$var reg 1 %" and_result $end
$var reg 1 &" and_gate $end
$upscope $end
$scope module and_output4 $end
$var reg 1 '" input1 $end
$var reg 1 (" input2 $end
$var reg 1 )" input3 $end
$var reg 1 *" and_result $end
$var reg 1 +" and_gate $end
$upscope $end
$upscope $end
$scope module and_gate_assignment(2) $end
$scope module and_output1 $end
$var reg 1 ," input1 $end
$var reg 1 -" input2 $end
$var reg 1 ." input3 $end
$var reg 1 /" and_result $end
$var reg 1 0" and_gate $end
$upscope $end
$scope module and_output2 $end
$var reg 1 1" input1 $end
$var reg 1 2" input2 $end
$var reg 1 3" input3 $end
$var reg 1 4" and_result $end
$var reg 1 5" and_gate $end
$upscope $end
$scope module and_output3 $end
$var reg 1 6" input1 $end
$var reg 1 7" input2 $end
$var reg 1 8" input3 $end
$var reg 1 9" and_result $end
$var reg 1 :" and_gate $end
$upscope $end
$scope module and_output4 $end
$var reg 1 ;" input1 $end
$var reg 1 <" input2 $end
$var reg 1 =" input3 $end
$var reg 1 >" and_result $end
$var reg 1 ?" and_gate $end
$upscope $end
$upscope $end
$upscope $end
$scope module demux14_1 $end
$var reg 3 @" y[2:0] $end
$var reg 2 A" sel[1:0] $end
$var reg 3 B" y0[2:0] $end
$var reg 3 C" y1[2:0] $end
$var reg 3 D" y2[2:0] $end
$var reg 3 E" y3[2:0] $end
$var reg 2 F" not_sel[1:0] $end
$scope module not_output0 $end
$var reg 1 G" input $end
$var reg 1 H" not_result $end
$var reg 1 I" not_gate $end
$upscope $end
$scope module not_output1 $end
$var reg 1 J" input $end
$var reg 1 K" not_result $end
$var reg 1 L" not_gate $end
$upscope $end
$scope module and_gate_assignment(0) $end
$scope module and_output1 $end
$var reg 1 M" input1 $end
$var reg 1 N" input2 $end
$var reg 1 O" input3 $end
$var reg 1 P" and_result $end
$var reg 1 Q" and_gate $end
$upscope $end
$scope module and_output2 $end
$var reg 1 R" input1 $end
$var reg 1 S" input2 $end
$var reg 1 T" input3 $end
$var reg 1 U" and_result $end
$var reg 1 V" and_gate $end
$upscope $end
$scope module and_output3 $end
$var reg 1 W" input1 $end
$var reg 1 X" input2 $end
$var reg 1 Y" input3 $end
$var reg 1 Z" and_result $end
$var reg 1 [" and_gate $end
$upscope $end
$scope module and_output4 $end
$var reg 1 \" input1 $end
$var reg 1 ]" input2 $end
$var reg 1 ^" input3 $end
$var reg 1 _" and_result $end
$var reg 1 `" and_gate $end
$upscope $end
$upscope $end
$scope module and_gate_assignment(1) $end
$scope module and_output1 $end
$var reg 1 a" input1 $end
$var reg 1 b" input2 $end
$var reg 1 c" input3 $end
$var reg 1 d" and_result $end
$var reg 1 e" and_gate $end
$upscope $end
$scope module and_output2 $end
$var reg 1 f" input1 $end
$var reg 1 g" input2 $end
$var reg 1 h" input3 $end
$var reg 1 i" and_result $end
$var reg 1 j" and_gate $end
$upscope $end
$scope module and_output3 $end
$var reg 1 k" input1 $end
$var reg 1 l" input2 $end
$var reg 1 m" input3 $end
$var reg 1 n" and_result $end
$var reg 1 o" and_gate $end
$upscope $end
$scope module and_output4 $end
$var reg 1 p" input1 $end
$var reg 1 q" input2 $end
$var reg 1 r" input3 $end
$var reg 1 s" and_result $end
$var reg 1 t" and_gate $end
$upscope $end
$upscope $end
$scope module and_gate_assignment(2) $end
$scope module and_output1 $end
$var reg 1 u" input1 $end
$var reg 1 v" input2 $end
$var reg 1 w" input3 $end
$var reg 1 x" and_result $end
$var reg 1 y" and_gate $end
$upscope $end
$scope module and_output2 $end
$var reg 1 z" input1 $end
$var reg 1 {" input2 $end
$var reg 1 |" input3 $end
$var reg 1 }" and_result $end
$var reg 1 !# and_gate $end
$upscope $end
$scope module and_output3 $end
$var reg 1 "# input1 $end
$var reg 1 ## input2 $end
$var reg 1 $# input3 $end
$var reg 1 %# and_result $end
$var reg 1 &# and_gate $end
$upscope $end
$scope module and_output4 $end
$var reg 1 '# input1 $end
$var reg 1 (# input2 $end
$var reg 1 )# input3 $end
$var reg 1 *# and_result $end
$var reg 1 +# and_gate $end
$upscope $end
$upscope $end
$upscope $end
$upscope $end
$upscope $end
$enddefinitions $end
#0
b111 !
b000 "
b111 #
b000 $
b000 %
b000 &
b000 '
b000 (
b000 )
b000 *
b111 +
b000 ,
b111 -
b000 .
b000 /
b000 0
b000 1
b000 2
b000 3
b000 4
b111 5
b000 6
b00 7
18
09
1:
1;
1<
1=
1>
1?
1@
0A
0B
0C
1D
1E
1F
1G
1H
0I
0J
0K
1L
1M
1N
1O
1P
0Q
0R
0S
b111 T
b00 U
b111 V
b000 W
b000 X
b000 Y
b11 Z
0[
1\
1]
0^
1_
1`
1a
1b
1c
1d
1e
1f
0g
1h
0i
0j
0k
1l
1m
0n
0o
0p
0q
1r
0s
0t
1u
1v
1w
1x
1y
1z
0{
1|
0}
0!"
0""
1#"
1$"
0%"
0&"
0'"
0("
1)"
0*"
0+"
1,"
1-"
1."
1/"
10"
11"
02"
13"
04"
05"
06"
17"
18"
09"
0:"
0;"
0<"
1="
0>"
0?"
b000 @"
b00 A"
b000 B"
b000 C"
b000 D"
b000 E"
b11 F"
0G"
1H"
1I"
0J"
1K"
1L"
1M"
1N"
0O"
0P"
0Q"
1R"
0S"
0T"
0U"
0V"
0W"
1X"
0Y"
0Z"
0["
0\"
0]"
0^"
0_"
0`"
1a"
1b"
0c"
0d"
0e"
1f"
0g"
0h"
0i"
0j"
0k"
1l"
0m"
0n"
0o"
0p"
0q"
0r"
0s"
0t"
1u"
1v"
0w"
0x"
0y"
1z"
0{"
0|"
0}"
0!#
0"#
1##
0$#
0%#
0&#
0'#
0(#
0)#
0*#
0+#
#10000000
b010 "
b000 #
b111 %
b010 ,
b000 -
b111 /
b10 7
b10 U
b000 V
b111 X
b01 Z
1^
0_
0`
0a
0d
0e
0f
1k
1n
1o
1p
0u
0x
0y
0z
1""
1%"
1&"
1'"
0,"
0/"
00"
01"
16"
19"
1:"
1;"
b10 A"
b01 F"
1J"
0K"
0L"
0M"
0R"
1W"
1\"
0a"
0f"
1k"
1p"
0u"
0z"
1"#
1'#
#20000000
b001 "
b111 $
b000 %
b001 ,
b111 .
b000 /
b01 7
b01 U
b111 W
b000 X
b10 Z
1[
0\
0]
0^
1_
1`
1a
0b
1f
1g
1i
1j
0k
0l
0n
0o
0p
1q
1u
0v
1z
1{
1}
1!"
0""
0#"
0%"
0&"
0'"
1("
1,"
0-"
11"
12"
14"
15"
06"
07"
09"
0:"
0;"
1<"
b01 A"
b10 F"
1G"
0H"
0I"
0J"
1K"
1L"
1M"
0N"
1R"
1S"
0W"
0X"
0\"
1]"
1a"
0b"
1f"
1g"
0k"
0l"
0p"
1q"
1u"
0v"
1z"
1{"
0"#
0##
0'#
1(#
#30000000
b011 "
b000 $
b111 &
b011 ,
b000 .
b111 0
b11 7
b11 U
b000 W
b111 Y
b00 Z
1^
0_
0`
0a
0f
0i
0j
1k
1p
1s
1t
0u
0z
0}
0!"
1""
1'"
1*"
1+"
0,"
01"
04"
05"
16"
1;"
1>"
1?"
b11 A"
b00 F"
1J"
0K"
0L"
0M"
0R"
1W"
1\"
0a"
0f"
1k"
1p"
0u"
0z"
1"#
1'#
#40000000
b100 "
b000 #
b000 &
b111 '
b100 ,
b000 -
b000 0
b111 1
b000 5
b111 6
b00 7
08
19
0:
0;
0=
0>
0?
1A
1B
1C
0E
0F
0G
1I
1J
1K
0M
0N
0O
1Q
1R
1S
b000 T
b00 U
b000 V
b000 Y
b11 Z
0[
1\
1]
0^
1_
1`
1a
1b
0c
0d
0e
1f
0g
0h
0k
1l
0m
0p
0q
0r
0s
0t
1u
1v
0w
0x
0y
1z
0{
0|
0""
1#"
0$"
0'"
0("
0)"
0*"
0+"
1,"
1-"
0."
0/"
00"
11"
02"
03"
06"
17"
08"
0;"
0<"
0="
0>"
0?"
b111 @"
b00 A"
b111 B"
b11 F"
0G"
1H"
1I"
0J"
1K"
1L"
1M"
1N"
1O"
1P"
1Q"
1R"
0S"
1T"
0W"
1X"
1Y"
0\"
0]"
1^"
1a"
1b"
1c"
1d"
1e"
1f"
0g"
1h"
0k"
1l"
1m"
0p"
0q"
1r"
1u"
1v"
1w"
1x"
1y"
1z"
0{"
1|"
0"#
1##
1$#
0'#
0(#
1)#
#50000000
b110 "
b000 '
b111 )
b110 ,
b000 1
b111 3
b10 7
b10 U
b01 Z
1^
0_
0`
0a
0f
1k
1p
0u
0z
1""
1'"
0,"
01"
16"
1;"
b10 A"
b000 B"
b111 D"
b01 F"
1J"
0K"
0L"
0M"
0P"
0Q"
0R"
1W"
1Z"
1["
1\"
0a"
0d"
0e"
0f"
1k"
1n"
1o"
1p"
0u"
0x"
0y"
0z"
1"#
1%#
1&#
1'#
#60000000
b101 "
b111 (
b000 )
b101 ,
b111 2
b000 3
b01 7
b01 U
b10 Z
1[
0\
0]
0^
1_
1`
1a
0b
1f
1g
0k
0l
0p
1q
1u
0v
1z
1{
0""
0#"
0'"
1("
1,"
0-"
11"
12"
06"
07"
0;"
1<"
b01 A"
b111 C"
b000 D"
b10 F"
1G"
0H"
0I"
0J"
1K"
1L"
1M"
0N"
1R"
1S"
1U"
1V"
0W"
0X"
0Z"
0["
0\"
1]"
1a"
0b"
1f"
1g"
1i"
1j"
0k"
0l"
0n"
0o"
0p"
1q"
1u"
0v"
1z"
1{"
1}"
1!#
0"#
0##
0%#
0&#
0'#
1(#
#70000000
b111 "
b000 (
b111 *
b111 ,
b000 2
b111 4
b11 7
b11 U
b00 Z
1^
0_
0`
0a
0f
1k
1p
0u
0z
1""
1'"
0,"
01"
16"
1;"
b11 A"
b000 C"
b111 E"
b00 F"
1J"
0K"
0L"
0M"
0R"
0U"
0V"
1W"
1\"
1_"
1`"
0a"
0f"
0i"
0j"
1k"
1p"
1s"
1t"
0u"
0z"
0}"
0!#
1"#
1'#
1*#
1+#
