Blatt_02/2d/2/andgate.vhdl
-- from the ieee libary we use std_logic_1164
-- defines a standard for logic values used in electronic design
-- for more info check the std_logic_1164.vhdl file in ghdl/libraries/ieee
-- ieee libary also defines operators and keywords
library ieee;
use ieee.std_logic_1164.all;
-- define signal (fundamental unit in vhdl) of type std_logic, called and_gate
-- and_gate gets assigned "input1 and input2"
--
--signal and_gate: std_logic;
--and_gate <= input1 and input2;

-- inputs and outputs of a file (andgate.vhdl) are defined in entities (black boxes)
-- entity has port that defines all inputs and outputs of file
-- like a header file (.h)
-- std_logic can have 9 different values, it is part of std_logic_1164 package
-- you can think of it as a single bit
entity andgate is
  port (
    input1 : in std_logic;
    input2 : in std_logic;
    and_result : out std_logic
  );
end andgate;

-- architecture describes functionality of particular entity
-- like .c implementation of a function
-- actually describes the "internal wiring" of block
architecture rtl of andgate is
  -- interconnection signals, constants, or other components
  signal and_gate : std_logic;
  signal dInput1 : std_logic;
  signal dInput2 : std_logic;
begin
  dInput1 <= input1 after 10 ns;
  dInput2 <= input2 after 10 ns;
  and_gate <= dInput1 and dInput2;
  and_result <= transport and_gate after 15 ns;
end rtl;

Blatt_02/Gruppe054_Blatt2/2_2/d/2/andgate_tb.vhdl
library ieee;
use ieee.std_logic_1164.all;

-- create testbench for and_gate
-- can be left empty, since test bench (this file) has no inputs or outputs
entity andgate_tb is
end andgate_tb;

architecture test of andgate_tb is
  -- component declaration, so that it can be instantiated later
  -- must have same name and port list as the entity
  component andgate
      port (
        input1 : in std_logic;
        input2 : in std_logic;
        and_result : out std_logic
      );
  end component;
-- define the signals that will be used in test
  signal a, b, c : std_logic;
-- begin test code
begin
  -- creates an instance of andgate
  and_g: andgate port map(input1 => a, input2 => b, and_result => c );

  process begin
    a <= '0';
    b <= '0';
    wait for 10 ns;
    a <= '0';
    b <= '1';       -- peak wird unterdrueckt
    wait for 10 ns;
    a <= '1';
    b <= '0';
    wait for 10 ns;
    a <= '1';
    b <= '1';       -- peak wird unterdrueckt
    wait for 10 ns;
    a <= 'X';
    b <= 'W';
    wait for 10 ns;
    assert false report "End of test";
    wait;
  end process;
end test;

Blatt_02/Gruppe054_Blatt2/2_2/d/2/testbench.vcd
$date
  Fri Oct 29 11:16:26 2021
$end
$version
  GHDL v0
$end
$timescale
  1 fs
$end
$scope module standard $end
$upscope $end
$scope module std_logic_1164 $end
$upscope $end
$scope module andgate_tb $end
$var reg 1 ! a $end
$var reg 1 " b $end
$var reg 1 # c $end
$scope module and_g $end
$var reg 1 $ input1 $end
$var reg 1 % input2 $end
$var reg 1 & and_result $end
$var reg 1 ' and_gate $end
$var reg 1 ( dinput1 $end
$var reg 1 ) dinput2 $end
$upscope $end
$upscope $end
$enddefinitions $end
#0
0!
0"
U#
0$
0%
U&
U'
U(
U)
#10000000
1"
1%
0'
0(
0)
#15000000
U&
#20000000
1!
0"
1$
0%
1)
#25000000
0#
0&
#30000000
1"
1%
1(
0)
#40000000
X!
W"
X$
W%
1'
1)
#50000000
X'
X(
W)
#55000000
1#
1&
#65000000
X#
X&
